Metadata-Version: 2.4
Name: llm-fragments-doc
Version: 0.1.1
Summary: Load documents as fragments
Author: Maximilian Bode
License: Apache-2.0
License-File: LICENSE
Classifier: License :: OSI Approved :: Apache Software License
Requires-Python: >=3.9
Requires-Dist: docling>=2.30.0
Requires-Dist: llm>=0.24
